setup.py
blender_file.egg-info/PKG-INFO
blender_file.egg-info/SOURCES.txt
blender_file.egg-info/dependency_links.txt
blender_file.egg-info/not-zip-safe
blender_file.egg-info/top_level.txt
blendfile/__init__.py