Metadata-Version: 1.0
Name: blender-file
Version: 1.0
Summary: Blender File
Home-page: https://developer.blender.org/diffusion/BBF/
Author: At Mind B.V. - Jeroen Bakker, Blender Foundation - Campbell Barton
Author-email: foundation@blender.org
License: GNU General Public License v2 or later (GPLv2+)
Platform: UNKNOWN
